jokegenerate/__init__.py
jokegenerate-0.2.dist-info/METADATA
jokegenerate-0.2.dist-info/WHEEL
jokegenerate-0.2.dist-info/license.txt
jokegenerate-0.2.dist-info/top_level.txt
jokegenerate-0.2.dist-info/RECORD
