Metadata-Version: 2.1
Name: jokegenerate
Version: 0.2
Summary: This is module is made by Saksham Jain
Home-page: UNKNOWN
Author: Saksham Jain
License: UNKNOWN
Platform: UNKNOWN
License-File: license.txt
